fastrpc/__init__.py
fastrpc/file_handler.py
fastrpc/todo.py
mu/__init__.py
mu/file_handler.py
mu/todo.py
page/__init__.py
page/file_handler.py
page/todo.py
pytodos/__init__.py
pytodos/file_handler.py
pytodos/todo.py
rapidrpc/__init__.py
rapidrpc/file_handler.py
rapidrpc/todo.py
yy/__init__.py
yy/file_handler.py
yy/todo.py
yy-1.0.16.dist-info/DESCRIPTION.rst
yy-1.0.16.dist-info/METADATA
yy-1.0.16.dist-info/RECORD
yy-1.0.16.dist-info/WHEEL
yy-1.0.16.dist-info/entry_points.txt
yy-1.0.16.dist-info/metadata.json
yy-1.0.16.dist-info/top_level.txt
